visualize_training/__init__.py
visualize_training/compute_cka.py
visualize_training/compute_cka_mnist.py
visualize_training/constants.py
visualize_training/data.py
visualize_training/hmm.py
visualize_training/metrics.py
visualize_training/model.py
visualize_training/train.py
visualize_training/utils.py
visualize_training/visualize.py
visualize_training/training/__init__.py
visualize_training/training/computer_vision.py
visualize_training/training/modular_addition.py
visualizing_training-1.0.0.dist-info/LICENSE
visualizing_training-1.0.0.dist-info/METADATA
visualizing_training-1.0.0.dist-info/WHEEL
visualizing_training-1.0.0.dist-info/top_level.txt
visualizing_training-1.0.0.dist-info/RECORD
