Metadata-Version: 2.1
Name: visualizing-training
Version: 1.0.0
Summary: Modelling Training Dynamics and Interpreting the dynamics
Project-URL: Homepage, https://github.com/michahu/visualizing-training
Requires-Python: >=3.9
License-File: LICENSE
Requires-Dist: numpy >=1.25.2
Requires-Dist: pandas >=2.2.1
Requires-Dist: evaluate >=0.4.1
Requires-Dist: torch >=2.2.2
Requires-Dist: accelerate >=0.28.0
Requires-Dist: wandb >=0.16.5
Requires-Dist: einops >=0.7.0
Requires-Dist: torchvision >=0.17.2
Requires-Dist: hmmlearn >=0.3.2
Requires-Dist: graphviz >=0.20.3
Requires-Dist: plotly >=5.20.0
Requires-Dist: gravis >=0.1.0
